wkey/__init__.py
wkey/find_key.py
wkey/listener.py
wkey/oa.py
wkey/process.py
wkey/utils.py
wkey/whisper.py
wkey/wkey.py
wkey-0.2.data/scripts/fkey
wkey-0.2.data/scripts/listen
wkey-0.2.data/scripts/listener.py
wkey-0.2.data/scripts/wkey
wkey-0.2.dist-info/METADATA
wkey-0.2.dist-info/WHEEL
wkey-0.2.dist-info/top_level.txt
wkey-0.2.dist-info/RECORD
